code_snapshot/__init__.py
code_snapshot/code_snapshot.py
code_snapshot/models.py
code_snapshot-0.2.4.dist-info/LICENSE
code_snapshot-0.2.4.dist-info/METADATA
code_snapshot-0.2.4.dist-info/WHEEL
code_snapshot-0.2.4.dist-info/top_level.txt
code_snapshot-0.2.4.dist-info/RECORD
