Metadata-Version: 2.1
Name: code-snapshot
Version: 0.2.4
Summary: code_snapshot - A Python library for interacting with the Showcode api.
Home-page: https://github.com/ainomic/code-snapshot
Author: Ainomic Technology
Author-email: contact@ainomic.in
License: GNU General Public License (GPL)
Keywords: snapshot,screenshot,code-snapshot,code-screenshot
Platform: ALL
Classifier: License :: OSI Approved :: GNU General Public License (GPL)
Classifier: Programming Language :: Python
Classifier: Programming Language :: Python :: 3
Classifier: Programming Language :: Python :: 3.8
License-File: LICENSE
Requires-Dist: requests (<2.32,>=2.31.0)
Requires-Dist: certifi
